{
  "slug": "san-francisco-state-university",
  "name": "San Francisco State University",
  "ipeds_id": 122597,
  "state": "CA",
  "city": "San Francisco",
  "type": "public",
  "scorecard": {
    "source": "College Scorecard",
    "retrieved": "2026-02-21",
    "admit_rate": 0.9615,
    "sat_reading_25": null,
    "sat_reading_75": null,
    "sat_math_25": null,
    "sat_math_75": null,
    "act_25": null,
    "act_75": null,
    "tuition_in_state": 7424,
    "tuition_out_of_state": 19304,
    "room_board": 17955,
    "total_cost_in_state": 27379,
    "total_cost_out_of_state": 39259,
    "net_price": {
      "0_30k": 9307,
      "30_48k": 10251,
      "48_75k": 12916,
      "75_110k": 16944,
      "110k_plus": 22813
    },
    "pell_rate": 0.414,
    "federal_loan_rate": 0.2543,
    "enrollment": 20033
  },
  "cds": null,
  "reference": null
}